prediction_strength/__init__.py
prediction_strength/prediction_strength.py
prediction_strength-0.1.0.dist-info/LICENSE
prediction_strength-0.1.0.dist-info/METADATA
prediction_strength-0.1.0.dist-info/WHEEL
prediction_strength-0.1.0.dist-info/RECORD
