Metadata-Version: 2.1
Name: prediction-strength
Version: 0.1.0
Summary: 
Author: Hubert Kozubek
Author-email: hkozubek00@gmail.com
Requires-Python: >=3.12,<4.0
Classifier: Programming Language :: Python :: 3
Classifier: Programming Language :: Python :: 3.12
Requires-Dist: numpy (>=1.26.4,<2.0.0)
